color_generator/__init__.py
color_generator/exceptions.py
color_generator/color/__init__.py
color_generator/color/__init__.pyi
color_generator/color/color_class.py
color_generator/generator/__init__.py
color_generator/generator/generate.py
color_generator/generator/generators.py
color_generator/generator/register.py
color_generation-0.3.0.dist-info/LICENSE
color_generation-0.3.0.dist-info/METADATA
color_generation-0.3.0.dist-info/WHEEL
color_generation-0.3.0.dist-info/top_level.txt
color_generation-0.3.0.dist-info/RECORD
