Metadata-Version: 2.1
Name: color-generation
Version: 0.3.0
Summary: generate random good-looking colors
Home-page: https://github.com/utility-libraries/color-generation-py
Author: PlayerG9
License: MIT
Project-URL: Author Github, https://github.com/PlayerG9
Project-URL: Organization Github, https://github.com/utility-libraries
Project-URL: Bug Tracker, https://github.com/utility-libraries/color-generation-py/issues
Classifier: Programming Language :: Python :: 3
Classifier: Programming Language :: Python :: 3 :: Only
Classifier: Programming Language :: Python :: 3.6
Classifier: Programming Language :: Python :: 3.7
Classifier: Programming Language :: Python :: 3.8
Classifier: Programming Language :: Python :: 3.9
Classifier: Programming Language :: Python :: 3.10
Classifier: Programming Language :: Python :: 3.11
Classifier: Programming Language :: Python :: 3.12
Classifier: Programming Language :: Python :: 3.13
Classifier: License :: OSI Approved :: MIT License
Classifier: Operating System :: OS Independent
Classifier: Topic :: Utilities
Requires-Python: >=3.5
License-File: LICENSE
